unknowncode/__init__.py
unknowncode-0.2.5.dist-info/WHEEL
unknowncode-0.2.5.dist-info/METADATA
unknowncode-0.2.5.dist-info/RECORD
