Metadata-Version: 2.1
Name: unknowncode
Version: 0.2.5
Summary: Small portions of code I use, gathered into one group for ease of access. Like a mod library for a game. Built with poetry
License: MIT
Keywords: library,Quality of Life,QoL
Author: UnknownSources
Requires-Python: >=3.10,<4.0
Classifier: License :: OSI Approved :: MIT License
Classifier: Programming Language :: Python :: 3
Classifier: Programming Language :: Python :: 3.10
